tepezza/__init__.py
tepezza/__main__.py
tepezza/__version__.py
tepezza/api.py
tepezza/hotkey.py
tepezza/data/default_config.ini
tepezza/data/get_master_zipcode_list.ipynb
tepezza/data/zipcodes.csv
tepezza-1.0.6.dist-info/LICENSE
tepezza-1.0.6.dist-info/METADATA
tepezza-1.0.6.dist-info/WHEEL
tepezza-1.0.6.dist-info/top_level.txt
tepezza-1.0.6.dist-info/RECORD
