Metadata-Version: 2.1
Name: tepezza
Version: 1.0.6
Summary: Scrape doctor data from www.tepezza.com
Home-page: https://github.com/2435191/TepezzaScraper
Author: Will Bradley
Author-email: derivativedude123@gmail.com
License: UNKNOWN
Project-URL: Bug Tracker, https://github.com/2435191/TepezzaScraper/issues
Platform: UNKNOWN
Classifier: Programming Language :: Python :: 3
Classifier: License :: OSI Approved :: MIT License
Classifier: Operating System :: OS Independent
Requires-Dist: clipboard
Requires-Dist: pandas
